nonebot_plugin_pychatgpt/__about__.py
nonebot_plugin_pychatgpt/__init__.py
nonebot_plugin_pychatgpt-0.0.1.dist-info/METADATA
nonebot_plugin_pychatgpt-0.0.1.dist-info/WHEEL
nonebot_plugin_pychatgpt-0.0.1.dist-info/licenses/LICENSE.txt
nonebot_plugin_pychatgpt-0.0.1.dist-info/RECORD
